CHANGELOG.md
LICENSE.txt
MANIFEST.in
README.md
requirements.txt
setup.py
webpack/__init__.py
webpack/apps.py
webpack/build_server.py
webpack/bundle.py
webpack/compiler.py
webpack/conf.py
webpack/django_integration.py
webpack/exceptions.py
webpack/manifest.py
webpack/options.py
webpack/resolver.py
webpack.egg-info/PKG-INFO
webpack.egg-info/SOURCES.txt
webpack.egg-info/dependency_links.txt
webpack.egg-info/pbr.json
webpack.egg-info/requires.txt
webpack.egg-info/top_level.txt
webpack/management/__init__.py
webpack/management/commands/__init__.py
webpack/management/commands/webpack.py
webpack/templatetags/__init__.py
webpack/templatetags/webpack.py