Metadata-Version: 1.0
Name: webpack
Version: 5.0.2
Summary: Python bindings to Webpack
Home-page: https://github.com/markfinger/python-webpack
Author: Mark Finger
Author-email: markfinger@gmail.com
License: UNKNOWN
Platform: UNKNOWN
